Metadata-Version: 2.1
Name: Flask-S3-ng
Version: 1.0.1
Summary: New Generation version of Flask-S3 project. Seamlessly serve the static files of your Flask app from Amazon S3
Home-page: http://github.com/cr0hn/flask-s3
Author: Edward Robinson
Author-email: hi@edd.io
Maintainer: cr0hn (maintainer)
Maintainer-email: cr0hn@cr0hn.com
License: License :: OSI Approved :: BSD License
Platform: UNKNOWN
Classifier: License :: OSI Approved :: BSD License
Classifier: Programming Language :: Python :: 3.8
Classifier: Environment :: Web Environment
Classifier: Intended Audience :: Developers
Classifier: License :: Other/Proprietary License
Classifier: Operating System :: OS Independent
Classifier: Programming Language :: Python
Classifier: Topic :: Internet :: WWW/HTTP :: Dynamic Content
Classifier: Topic :: Software Development :: Libraries :: Python Modules
